kosmoy_data_sdk/__init__.py
kosmoy_data_sdk/kosmoy_data_sdk.py
kosmoy_data_sdk/schemas_sdk.py
kosmoy_data_sdk-0.4.2.dist-info/METADATA
kosmoy_data_sdk-0.4.2.dist-info/WHEEL
kosmoy_data_sdk-0.4.2.dist-info/top_level.txt
kosmoy_data_sdk-0.4.2.dist-info/RECORD
