Metadata-Version: 2.1
Name: kosmoy-data-sdk
Version: 0.4.2
Summary: SDK to get all the available LLM models per Provider
Author: Olsi Hoxha
Author-email: olsihoxha824@gmail.com
Classifier: Programming Language :: Python :: 3
Classifier: License :: OSI Approved :: MIT License
Classifier: Operating System :: OS Independent
Requires-Python: >=3.6
Requires-Dist: requests
Requires-Dist: pydantic
